[{"link_title": null, "guid": "03b9220bac5b4b08a8826a75192faabf", "description": null, "fips_class": "C1", "url": "http://www.ci.arlington.wa.us/", "feature_id": "34048", "state_name": "Washington", "fips_county_cd": "61", "state_abbreviation": "WA", "full_county_name": "Snohomish County", "county_name": "Snohomish", "feat_class": "Populated Place", "primary_latitude": "48.19", "primary_longitude": "-122.12", "name": "Arlington"}, {"link_title": null, "guid": "de998b474e8d4bf888f4e62f8c57f26f", "description": null, "fips_class": "C1", "url": "http://www.washougal.biz/", "feature_id": "34304", "state_name": "Washington", "fips_county_cd": "11", "state_abbreviation": "WA", "full_county_name": "Clark County", "county_name": "Clark", "feat_class": "Populated Place", "primary_latitude": "45.58", "primary_longitude": "-122.35", "name": "Washougal"}, {"link_title": null, "guid": "e551dc9b007a452e9217189e0cbeb4f5", "description": null, "fips_class": "C1", "url": "http://www.ci.auburn.wa.us/", "feature_id": "34050", "state_name": "Washington", "fips_county_cd": "33", "state_abbreviation": "WA", "full_county_name": "King County", "county_name": "King", "feat_class": "Populated Place", "primary_latitude": "47.3", "primary_longitude": "-122.22", "name": "Auburn"}, {"link_title": null, "guid": "8d64c6cabe1b41f192f8233810a0145e", "description": null, "fips_class": "C1", "url": "http://www.ci.waterville.wa.us/", "feature_id": "34306", "state_name": "Washington", "fips_county_cd": "17", "state_abbreviation": "WA", "full_county_name": "Douglas County", "county_name": "Douglas", "feat_class": "Populated Place", "primary_latitude": "47.64", "primary_longitude": "-120.07", "name": "Waterville"}, {"link_title": null, "guid": "ed7d62ce1fa749a98fe75e7b106b6e00", "description": null, "fips_class": "C1", "url": "http://www.cityofbg.org/", "feature_id": "34052", "state_name": "Washington", "fips_county_cd": "11", "state_abbreviation": "WA", "full_county_name": "Clark County", "county_name": "Clark", "feat_class": "Populated Place", "primary_latitude": "45.78", "primary_longitude": "-122.53", "name": "Battle Ground"}, {"link_title": null, "guid": "66d0f44a9c8b4c77aacf465e2ca7798f", "description": null, "fips_class": "C1", "url": "http://www.wenatcheewa.gov/", "feature_id": "34308", "state_name": "Washington", "fips_county_cd": "7", "state_abbreviation": "WA", "full_county_name": "Chelan County", "county_name": "Chelan", "feat_class": "Populated Place", "primary_latitude": "47.42", "primary_longitude": "-120.31", "name": "Wenatchee"}, {"link_title": null, "guid": "1d902ccaa037455cb5b86a8dd64b6829", "description": null, "fips_class": "C1", "url": "http://www.beauxarts-wa.gov/", "feature_id": "34053", "state_name": "Washington", "fips_county_cd": "33", "state_abbreviation": "WA", "full_county_name": "King County", "county_name": "King", "feat_class": "Populated Place", "primary_latitude": "47.58", "primary_longitude": "-122.19", "name": "Beaux Arts Village"}, {"link_title": null, "guid": "b38c57f2b82b4b5f84c2a2f8811f6af0", "description": null, "fips_class": "C1", "url": "http://www.ci.bellevue.wa.us/", "feature_id": "34054", "state_name": "Washington", "fips_county_cd": "33", "state_abbreviation": "WA", "full_county_name": "King County", "county_name": "King", "feat_class": "Populated Place", "primary_latitude": "47.61", "primary_longitude": "-122.2", "name": "Bellevue"}, {"link_title": null, "guid": "875f5515812544cda0c31ec3d80e0c2b", "description": null, "fips_class": "C1", "url": "http://ci.westport.wa.us/", "feature_id": "34310", "state_name": "Washington", "fips_county_cd": "27", "state_abbreviation": "WA", "full_county_name": "Grays Harbor County", "county_name": "Grays Harbor", "feat_class": "Populated Place", "primary_latitude": "46.89", "primary_longitude": "-124.1", "name": "Westport"}, {"link_title": null, "guid": "d6408358aa684e12bc3c8bea760363d2", "description": null, "fips_class": "C1", "url": "http://www.cob.org/", "feature_id": "34055", "state_name": "Washington", "fips_county_cd": "73", "state_abbreviation": "WA", "full_county_name": "Whatcom County", "county_name": "Whatcom", "feat_class": "Populated Place", "primary_latitude": "48.75", "primary_longitude": "-122.48", "name": "Bellingham"}, {"link_title": null, "guid": "fdcf3431bcf94d868cacb2f1b8dad88c", "description": null, "fips_class": "C1", "url": "http://ci.benton-city.wa.us/", "feature_id": "34056", "state_name": "Washington", "fips_county_cd": "5", "state_abbreviation": "WA", "full_county_name": "Benton County", "county_name": "Benton", "feat_class": "Populated Place", "primary_latitude": "46.26", "primary_longitude": "-119.48", "name": "Benton City"}, {"link_title": null, "guid": "de80e3d555414164bc1c69c7e4bf8535", "description": null, "fips_class": "C1", "url": "http://www.wilburwa.com/", "feature_id": "34312", "state_name": "Washington", "fips_county_cd": "43", "state_abbreviation": "WA", "full_county_name": "Lincoln County", "county_name": "Lincoln", "feat_class": "Populated Place", "primary_latitude": "47.75", "primary_longitude": "-118.7", "name": "Wilbur"}, {"link_title": null, "guid": "181fe1d3053948bf9ec28a030fa0ad54", "description": null, "fips_class": "C1", "url": "http://www.bingenwashington.org/", "feature_id": "34057", "state_name": "Washington", "fips_county_cd": "39", "state_abbreviation": "WA", "full_county_name": "Klickitat County", "county_name": "Klickitat", "feat_class": "Populated Place", "primary_latitude": "45.71", "primary_longitude": "-121.46", "name": "Bingen"}, {"link_title": null, "guid": "a94a8fa766fb4aeaa178a66d7f0a7529", "description": null, "fips_class": "C1", "url": "http://www.ci.blaine.wa.us/", "feature_id": "34059", "state_name": "Washington", "fips_county_cd": "73", "state_abbreviation": "WA", "full_county_name": "Whatcom County", "county_name": "Whatcom", "feat_class": "Populated Place", "primary_latitude": "48.99", "primary_longitude": "-122.74", "name": "Blaine"}, {"link_title": null, "guid": "6a03789deac44df1a75359e4cb19f110", "description": null, "fips_class": "C1", "url": "http://www.citybonneylake.org/", "feature_id": "34060", "state_name": "Washington", "fips_county_cd": "53", "state_abbreviation": "WA", "full_county_name": "Pierce County", "county_name": "Pierce", "feat_class": "Populated Place", "primary_latitude": "47.17", "primary_longitude": "-122.18", "name": "Bonney Lake"}, {"link_title": null, "guid": "cd7d28a409fa45b9ae75d4486f4b7b81", "description": null, "fips_class": "C1", "url": "http://www.ci.bothell.wa.us/", "feature_id": "34061", "state_name": "Washington", "fips_county_cd": "33", "state_abbreviation": "WA", "full_county_name": "King County", "county_name": "King", "feat_class": "Populated Place", "primary_latitude": "47.76", "primary_longitude": "-122.2", "name": "Bothell"}, {"link_title": null, "guid": "bbc6756b97fc44d8acd4685f2f856cc3", "description": null, "fips_class": "C1", "url": "http://www.ci.woodinville.wa.us/", "feature_id": "34317", "state_name": "Washington", "fips_county_cd": "33", "state_abbreviation": "WA", "full_county_name": "King County", "county_name": "King", "feat_class": "Populated Place", "primary_latitude": "47.75", "primary_longitude": "-122.16", "name": "Woodinville"}, {"link_title": null, "guid": "4d6f219ebf4e47adaad4e37044c3a176", "description": null, "fips_class": "C1", "url": "http://www.ci.bremerton.wa.us/", "feature_id": "34062", "state_name": "Washington", "fips_county_cd": "35", "state_abbreviation": "WA", "full_county_name": "Kitsap County", "county_name": "Kitsap", "feat_class": "Populated Place", "primary_latitude": "47.56", "primary_longitude": "-122.63", "name": "Bremerton"}, {"link_title": null, "guid": "d6e42e1868864a4aad53d2de3e1f0fe6", "description": null, "fips_class": "C1", "url": "http://www.ci.woodland.wa.us/", "feature_id": "34318", "state_name": "Washington", "fips_county_cd": "15", "state_abbreviation": "WA", "full_county_name": "Cowlitz County", "county_name": "Cowlitz", "feat_class": "Populated Place", "primary_latitude": "45.9", "primary_longitude": "-122.74", "name": "Woodland"}, {"link_title": null, "guid": "020d2d14449a4240961fa74263336540", "description": null, "fips_class": "C1", "url": "http://www.ci.brier.wa.us/", "feature_id": "34065", "state_name": "Washington", "fips_county_cd": "61", "state_abbreviation": "WA", "full_county_name": "Snohomish County", "county_name": "Snohomish", "feat_class": "Populated Place", "primary_latitude": "47.78", "primary_longitude": "-122.27", "name": "Brier"}, {"link_title": null, "guid": "223cd12e60404c9894c81e2129206e9f", "description": null, "fips_class": "C1", "url": "http://www.ci.yakima.wa.us/", "feature_id": "34321", "state_name": "Washington", "fips_county_cd": "77", "state_abbreviation": "WA", "full_county_name": "Yakima County", "county_name": "Yakima", "feat_class": "Populated Place", "primary_latitude": "46.6", "primary_longitude": "-120.5", "name": "Yakima"}, {"link_title": null, "guid": "a473f3d9a4664719a3bdefdcedab2c23", "description": null, "fips_class": "C1", "url": "http://www.ci.yarrow-point.wa.us/", "feature_id": "34322", "state_name": "Washington", "fips_county_cd": "33", "state_abbreviation": "WA", "full_county_name": "King County", "county_name": "King", "feat_class": "Populated Place", "primary_latitude": "47.64", "primary_longitude": "-122.21", "name": "Yarrow Point"}, {"link_title": null, "guid": "eea74ea88bed4bdb976109a47be38b82", "description": null, "fips_class": "C1", "url": "http://www.burienwa.gov/", "feature_id": "34068", "state_name": "Washington", "fips_county_cd": "33", "state_abbreviation": "WA", "full_county_name": "King County", "county_name": "King", "feat_class": "Populated Place", "primary_latitude": "47.47", "primary_longitude": "-122.34", "name": "Burien"}, {"link_title": null, "guid": "bb35aa9a8fdc4f43aaab3f78e8495dd0", "description": null, "fips_class": "C1", "url": "http://www.ci.burlington.wa.us/", "feature_id": "34069", "state_name": "Washington", "fips_county_cd": "57", "state_abbreviation": "WA", "full_county_name": "Skagit County", "county_name": "Skagit", "feat_class": "Populated Place", "primary_latitude": "48.47", "primary_longitude": "-122.32", "name": "Burlington"}, {"link_title": null, "guid": "8ddb99319cd04c0fa775879818f30bc9", "description": null, "fips_class": "C1", "url": "http://www.ci.camas.wa.us/", "feature_id": "34070", "state_name": "Washington", "fips_county_cd": "11", "state_abbreviation": "WA", "full_county_name": "Clark County", "county_name": "Clark", "feat_class": "Populated Place", "primary_latitude": "45.58", "primary_longitude": "-122.39", "name": "Camas"}, {"link_title": null, "guid": "257c6a07d4a94a65b07394942cfad914", "description": null, "fips_class": "C1", "url": "http://www.ci.carnation.wa.us/", "feature_id": "34072", "state_name": "Washington", "fips_county_cd": "33", "state_abbreviation": "WA", "full_county_name": "King County", "county_name": "King", "feat_class": "Populated Place", "primary_latitude": "47.64", "primary_longitude": "-121.91", "name": "Carnation"}, {"link_title": null, "guid": "b60b95e34a4444ffbf59e61cc081d8e6", "description": null, "fips_class": "C1", "url": "http://www.cityofcashmere.org/", "feature_id": "34073", "state_name": "Washington", "fips_county_cd": "7", "state_abbreviation": "WA", "full_county_name": "Chelan County", "county_name": "Chelan", "feat_class": "Populated Place", "primary_latitude": "47.52", "primary_longitude": "-120.46", "name": "Cashmere"}, {"link_title": null, "guid": "bb8bf4b5331744faa1ac76f6c8c53a16", "description": null, "fips_class": "C1", "url": "http://ci.castle-rock.wa.us/", "feature_id": "34074", "state_name": "Washington", "fips_county_cd": "15", "state_abbreviation": "WA", "full_county_name": "Cowlitz County", "county_name": "Cowlitz", "feat_class": "Populated Place", "primary_latitude": "46.27", "primary_longitude": "-122.9", "name": "Castle Rock"}, {"link_title": null, "guid": "ab8bafe8674a4a1c95a42e5a64b09235", "description": null, "fips_class": "C1", "url": "http://www.cityofcentralia.com/", "feature_id": "34076", "state_name": "Washington", "fips_county_cd": "41", "state_abbreviation": "WA", "full_county_name": "Lewis County", "county_name": "Lewis", "feat_class": "Populated Place", "primary_latitude": "46.71", "primary_longitude": "-122.95", "name": "Centralia"}, {"link_title": null, "guid": "d022306d1112486993fd924c7b125b29", "description": null, "fips_class": "C1", "url": "http://www.cityofchelan.com/", "feature_id": "34078", "state_name": "Washington", "fips_county_cd": "7", "state_abbreviation": "WA", "full_county_name": "Chelan County", "county_name": "Chelan", "feat_class": "Populated Place", "primary_latitude": "47.84", "primary_longitude": "-120.01", "name": "Chelan"}, {"link_title": null, "guid": "85932814e0dd43eba1aabf6e9324dea4", "description": null, "fips_class": "C1", "url": "http://www.cityofcheney.org/", "feature_id": "34079", "state_name": "Washington", "fips_county_cd": "63", "state_abbreviation": "WA", "full_county_name": "Spokane County", "county_name": "Spokane", "feat_class": "Populated Place", "primary_latitude": "47.48", "primary_longitude": "-117.57", "name": "Cheney"}, {"link_title": null, "guid": "d409f7eedd98400c8e61853609af3ff4", "description": null, "fips_class": "C1", "url": "http://www.clydehill.org/", "feature_id": "34083", "state_name": "Washington", "fips_county_cd": "33", "state_abbreviation": "WA", "full_county_name": "King County", "county_name": "King", "feat_class": "Populated Place", "primary_latitude": "47.63", "primary_longitude": "-122.21", "name": "Clyde Hill"}, {"link_title": null, "guid": "61a1a378fbe54121950f39f793d3dc59", "description": null, "fips_class": "C1", "url": "http://www.ci.colfax.wa.us/", "feature_id": "34084", "state_name": "Washington", "fips_county_cd": "75", "state_abbreviation": "WA", "full_county_name": "Whitman County", "county_name": "Whitman", "feat_class": "Populated Place", "primary_latitude": "46.88", "primary_longitude": "-117.36", "name": "Colfax"}, {"link_title": null, "guid": "25d2e928698340d98082c193e17b0c65", "description": null, "fips_class": "C1", "url": "http://ci.college-place.wa.us/", "feature_id": "34085", "state_name": "Washington", "fips_county_cd": "71", "state_abbreviation": "WA", "full_county_name": "Walla Walla County", "county_name": "Walla Walla", "feat_class": "Populated Place", "primary_latitude": "46.04", "primary_longitude": "-118.38", "name": "College Place"}, {"link_title": null, "guid": "9ce63e764efd4545b945331b283d3a0d", "description": null, "fips_class": "C1", "url": "http://www.townofconcrete.com/", "feature_id": "34089", "state_name": "Washington", "fips_county_cd": "57", "state_abbreviation": "WA", "full_county_name": "Skagit County", "county_name": "Skagit", "feat_class": "Populated Place", "primary_latitude": "48.53", "primary_longitude": "-121.74", "name": "Concrete"}, {"link_title": null, "guid": "043e17b755fd42c5b308c6d34202a4d4", "description": null, "fips_class": "C1", "url": "http://www.cityofconnell.com/", "feature_id": "34090", "state_name": "Washington", "fips_county_cd": "21", "state_abbreviation": "WA", "full_county_name": "Franklin County", "county_name": "Franklin", "feat_class": "Populated Place", "primary_latitude": "46.66", "primary_longitude": "-118.86", "name": "Connell"}, {"link_title": null, "guid": "364331eddae545f6ad652dcf0d703e66", "description": null, "fips_class": "C1", "url": "http://www.ci.covington.wa.us/", "feature_id": "34097", "state_name": "Washington", "fips_county_cd": "33", "state_abbreviation": "WA", "full_county_name": "King County", "county_name": "King", "feat_class": "Populated Place", "primary_latitude": "47.34", "primary_longitude": "-122.11", "name": "Covington"}, {"link_title": null, "guid": "1a53d323ecee4db0a7d1f9141b4ac6c0", "description": null, "fips_class": "C1", "url": "http://www.daytonwa.com/", "feature_id": "34102", "state_name": "Washington", "fips_county_cd": "13", "state_abbreviation": "WA", "full_county_name": "Columbia County", "county_name": "Columbia", "feat_class": "Populated Place", "primary_latitude": "46.32", "primary_longitude": "-117.97", "name": "Dayton"}, {"link_title": null, "guid": "08ce3fd87338410793317dbef5e55386", "description": null, "fips_class": "C1", "url": "http://www.desmoineswa.gov/", "feature_id": "34104", "state_name": "Washington", "fips_county_cd": "33", "state_abbreviation": "WA", "full_county_name": "King County", "county_name": "King", "feat_class": "Populated Place", "primary_latitude": "47.4", "primary_longitude": "-122.32", "name": "Des Moines"}, {"link_title": null, "guid": "309385067a8c411282b2f46b6514b57e", "description": null, "fips_class": "C1", "url": "http://www.ci.dupont.wa.us/", "feature_id": "34105", "state_name": "Washington", "fips_county_cd": "53", "state_abbreviation": "WA", "full_county_name": "Pierce County", "county_name": "Pierce", "feat_class": "Populated Place", "primary_latitude": "47.09", "primary_longitude": "-122.63", "name": "DuPont"}, {"link_title": null, "guid": "03de01f421de4984aef1ee6fa67a5967", "description": null, "fips_class": "C1", "url": "http://www.duvallwa.gov/", "feature_id": "34106", "state_name": "Washington", "fips_county_cd": "33", "state_abbreviation": "WA", "full_county_name": "King County", "county_name": "King", "feat_class": "Populated Place", "primary_latitude": "47.74", "primary_longitude": "-121.98", "name": "Duvall"}, {"link_title": null, "guid": "5082de048f14474685540e879f4aa366", "description": null, "fips_class": "C1", "url": "http://www.east-wenatchee.com/", "feature_id": "34107", "state_name": "Washington", "fips_county_cd": "17", "state_abbreviation": "WA", "full_county_name": "Douglas County", "county_name": "Douglas", "feat_class": "Populated Place", "primary_latitude": "47.41", "primary_longitude": "-120.29", "name": "East Wenatchee"}, {"link_title": null, "guid": "bbaa1fc06b5f46c985f8a3b9aaf40814", "description": null, "fips_class": "C1", "url": "http://www.cityofedgewood.org/", "feature_id": "34109", "state_name": "Washington", "fips_county_cd": "53", "state_abbreviation": "WA", "full_county_name": "Pierce County", "county_name": "Pierce", "feat_class": "Populated Place", "primary_latitude": "47.25", "primary_longitude": "-122.29", "name": "Edgewood"}, {"link_title": null, "guid": "b149a11ce45742d3b4e0fb0d31078235", "description": null, "fips_class": "C1", "url": "http://www.ci.edmonds.wa.us/", "feature_id": "34110", "state_name": "Washington", "fips_county_cd": "61", "state_abbreviation": "WA", "full_county_name": "Snohomish County", "county_name": "Snohomish", "feat_class": "Populated Place", "primary_latitude": "47.81", "primary_longitude": "-122.37", "name": "Edmonds"}, {"link_title": null, "guid": "f750d0aff3c14293a9cdaea730cfb198", "description": null, "fips_class": "C1", "url": "http://www.ci.ellensburg.wa.us/", "feature_id": "34112", "state_name": "Washington", "fips_county_cd": "37", "state_abbreviation": "WA", "full_county_name": "Kittitas County", "county_name": "Kittitas", "feat_class": "Populated Place", "primary_latitude": "46.99", "primary_longitude": "-120.54", "name": "Ellensburg"}, {"link_title": null, "guid": "7ec23c08ec46499988288c53098853d1", "description": null, "fips_class": "C1", "url": "http://www.ci.enumclaw.wa.us/", "feature_id": "34117", "state_name": "Washington", "fips_county_cd": "33", "state_abbreviation": "WA", "full_county_name": "King County", "county_name": "King", "feat_class": "Populated Place", "primary_latitude": "47.2", "primary_longitude": "-121.99", "name": "Enumclaw"}, {"link_title": null, "guid": "05bc7a5a63bb42caaf774db057e446e0", "description": null, "fips_class": "C1", "url": "http://www.ephrata.org/", "feature_id": "34118", "state_name": "Washington", "fips_county_cd": "25", "state_abbreviation": "WA", "full_county_name": "Grant County", "county_name": "Grant", "feat_class": "Populated Place", "primary_latitude": "47.31", "primary_longitude": "-119.55", "name": "Ephrata"}, {"link_title": null, "guid": "aa48149e9265428fa2c52feadc93d4d0", "description": null, "fips_class": "C1", "url": "http://www.ci.everett.wa.us/", "feature_id": "34119", "state_name": "Washington", "fips_county_cd": "61", "state_abbreviation": "WA", "full_county_name": "Snohomish County", "county_name": "Snohomish", "feat_class": "Populated Place", "primary_latitude": "47.97", "primary_longitude": "-122.2", "name": "Everett"}, {"link_title": null, "guid": "9bfb46f93d7544649de1e0a17b4462f0", "description": null, "fips_class": "C1", "url": "http://www.cityoffederalway.com/", "feature_id": "34123", "state_name": "Washington", "fips_county_cd": "33", "state_abbreviation": "WA", "full_county_name": "King County", "county_name": "King", "feat_class": "Populated Place", "primary_latitude": "47.32", "primary_longitude": "-122.31", "name": "Federal Way"}, {"link_title": null, "guid": "092be2262fec49f7b5c4dde14b483139", "description": null, "fips_class": "C1", "url": "http://www.ci.ferndale.wa.us/", "feature_id": "34124", "state_name": "Washington", "fips_county_cd": "73", "state_abbreviation": "WA", "full_county_name": "Whatcom County", "county_name": "Whatcom", "feat_class": "Populated Place", "primary_latitude": "48.84", "primary_longitude": "-122.59", "name": "Ferndale"}, {"link_title": null, "guid": "1e023ffb7e784c3ca3fd22e5b30be941", "description": null, "fips_class": "C1", "url": "http://www.cityoffife.org/", "feature_id": "34125", "state_name": "Washington", "fips_county_cd": "53", "state_abbreviation": "WA", "full_county_name": "Pierce County", "county_name": "Pierce", "feat_class": "Populated Place", "primary_latitude": "47.23", "primary_longitude": "-122.35", "name": "Fife"}, {"link_title": null, "guid": "63df7a4373314504b7cc43de49cb513e", "description": null, "fips_class": "C1", "url": "http://www.forkswashington.org/", "feature_id": "34127", "state_name": "Washington", "fips_county_cd": "9", "state_abbreviation": "WA", "full_county_name": "Clallam County", "county_name": "Clallam", "feat_class": "Populated Place", "primary_latitude": "47.95", "primary_longitude": "-124.38", "name": "Forks"}, {"link_title": null, "guid": "9ad101a920974edbb59826299cb72210", "description": null, "fips_class": "C1", "url": "http://www.fridayharbor.org/", "feature_id": "34128", "state_name": "Washington", "fips_county_cd": "55", "state_abbreviation": "WA", "full_county_name": "San Juan County", "county_name": "San Juan", "feat_class": "Populated Place", "primary_latitude": "48.53", "primary_longitude": "-123.01", "name": "Friday Harbor"}, {"link_title": null, "guid": "6fefc47790f44e2aa73ef12f2b686dc3", "description": null, "fips_class": "C1", "url": "http://www.ci.george.wa.us/", "feature_id": "34130", "state_name": "Washington", "fips_county_cd": "25", "state_abbreviation": "WA", "full_county_name": "Grant County", "county_name": "Grant", "feat_class": "Populated Place", "primary_latitude": "47.07", "primary_longitude": "-119.85", "name": "George"}, {"link_title": null, "guid": "9727111999ea4da19b48a2d56cebb242", "description": null, "fips_class": "C1", "url": "http://www.cityofgigharbor.net/", "feature_id": "34131", "state_name": "Washington", "fips_county_cd": "53", "state_abbreviation": "WA", "full_county_name": "Pierce County", "county_name": "Pierce", "feat_class": "Populated Place", "primary_latitude": "47.32", "primary_longitude": "-122.58", "name": "Gig Harbor"}, {"link_title": null, "guid": "8aa8733128ef4c9abea7fc266541e545", "description": null, "fips_class": "C1", "url": "http://www.grandview.wa.us/", "feature_id": "34135", "state_name": "Washington", "fips_county_cd": "77", "state_abbreviation": "WA", "full_county_name": "Yakima County", "county_name": "Yakima", "feat_class": "Populated Place", "primary_latitude": "46.25", "primary_longitude": "-119.9", "name": "Grandview"}, {"link_title": null, "guid": "13329c330f9340f494613c5301de31cc", "description": null, "fips_class": "C1", "url": "http://www.cityofhoquiam.com/", "feature_id": "34143", "state_name": "Washington", "fips_county_cd": "27", "state_abbreviation": "WA", "full_county_name": "Grays Harbor County", "county_name": "Grays Harbor", "feat_class": "Populated Place", "primary_latitude": "46.98", "primary_longitude": "-123.88", "name": "Hoquiam"}, {"link_title": null, "guid": "0c9331cdbd1b4714afe98f0ec136ee5f", "description": null, "fips_class": "C1", "url": "http://www.ilwacowashington.com/", "feature_id": "34145", "state_name": "Washington", "fips_county_cd": "49", "state_abbreviation": "WA", "full_county_name": "Pacific County", "county_name": "Pacific", "feat_class": "Populated Place", "primary_latitude": "46.3", "primary_longitude": "-124.04", "name": "Ilwaco"}, {"link_title": null, "guid": "f9d8001fbebc425b97f1f8399471d35d", "description": null, "fips_class": "C1", "url": "http://www.ci.issaquah.wa.us/", "feature_id": "34148", "state_name": "Washington", "fips_county_cd": "33", "state_abbreviation": "WA", "full_county_name": "King County", "county_name": "King", "feat_class": "Populated Place", "primary_latitude": "47.53", "primary_longitude": "-122.03", "name": "Issaquah"}, {"link_title": null, "guid": "d8ffd48eee9d4913b8c2bdd23f83574a", "description": null, "fips_class": "C1", "url": "http://www.cityofkalama.com/", "feature_id": "34150", "state_name": "Washington", "fips_county_cd": "15", "state_abbreviation": "WA", "full_county_name": "Cowlitz County", "county_name": "Cowlitz", "feat_class": "Populated Place", "primary_latitude": "46", "primary_longitude": "-122.84", "name": "Kalama"}, {"link_title": null, "guid": "62bee10b6aee484786063ef817ada81a", "description": null, "fips_class": "C1", "url": "http://www.kelso.gov/", "feature_id": "34151", "state_name": "Washington", "fips_county_cd": "15", "state_abbreviation": "WA", "full_county_name": "Cowlitz County", "county_name": "Cowlitz", "feat_class": "Populated Place", "primary_latitude": "46.14", "primary_longitude": "-122.9", "name": "Kelso"}, {"link_title": null, "guid": "8c5b696bb0d74a73ac4ba1195e8ad149", "description": null, "fips_class": "C1", "url": "http://www.cityofkenmore.com/", "feature_id": "34152", "state_name": "Washington", "fips_county_cd": "33", "state_abbreviation": "WA", "full_county_name": "King County", "county_name": "King", "feat_class": "Populated Place", "primary_latitude": "47.75", "primary_longitude": "-122.24", "name": "Kenmore"}, {"link_title": null, "guid": "b3f549675b0c48f58d747690679b5d79", "description": null, "fips_class": "C1", "url": "http://www.ci.kennewick.wa.us/", "feature_id": "34153", "state_name": "Washington", "fips_county_cd": "5", "state_abbreviation": "WA", "full_county_name": "Benton County", "county_name": "Benton", "feat_class": "Populated Place", "primary_latitude": "46.21", "primary_longitude": "-119.13", "name": "Kennewick"}, {"link_title": null, "guid": "3f967d9c342e473aaa9b44d3fe2d3973", "description": null, "fips_class": "C1", "url": "http://www.ci.kent.wa.us/", "feature_id": "34154", "state_name": "Washington", "fips_county_cd": "33", "state_abbreviation": "WA", "full_county_name": "King County", "county_name": "King", "feat_class": "Populated Place", "primary_latitude": "47.38", "primary_longitude": "-122.23", "name": "Kent"}, {"link_title": null, "guid": "f681c634c9914d2a8b2b652a25337bad", "description": null, "fips_class": "C1", "url": "http://www.ci.kirkland.wa.us/", "feature_id": "34156", "state_name": "Washington", "fips_county_cd": "33", "state_abbreviation": "WA", "full_county_name": "King County", "county_name": "King", "feat_class": "Populated Place", "primary_latitude": "47.68", "primary_longitude": "-122.2", "name": "Kirkland"}, {"link_title": null, "guid": "e4f556c42d22403ab956adf119ceaafa", "description": null, "fips_class": "C1", "url": "http://www.lacenterwa.com/", "feature_id": "34158", "state_name": "Washington", "fips_county_cd": "11", "state_abbreviation": "WA", "full_county_name": "Clark County", "county_name": "Clark", "feat_class": "Populated Place", "primary_latitude": "45.86", "primary_longitude": "-122.67", "name": "La Center"}, {"link_title": null, "guid": "b490eb7efced4d5c95d9b6e3c7a16fee", "description": null, "fips_class": "C1", "url": "http://www.laconner.net/", "feature_id": "34159", "state_name": "Washington", "fips_county_cd": "57", "state_abbreviation": "WA", "full_county_name": "Skagit County", "county_name": "Skagit", "feat_class": "Populated Place", "primary_latitude": "48.38", "primary_longitude": "-122.49", "name": "La Conner"}, {"link_title": null, "guid": "a19a8b927870447ba7c26805b94be17b", "description": null, "fips_class": "C1", "url": "http://www.ci.lacey.wa.us/", "feature_id": "34161", "state_name": "Washington", "fips_county_cd": "67", "state_abbreviation": "WA", "full_county_name": "Thurston County", "county_name": "Thurston", "feat_class": "Populated Place", "primary_latitude": "47.03", "primary_longitude": "-122.82", "name": "Lacey"}, {"link_title": null, "guid": "cd94f00c5e1147e1bd114e112c5da146", "description": null, "fips_class": "C1", "url": "http://www.cityoflfp.com/", "feature_id": "34162", "state_name": "Washington", "fips_county_cd": "33", "state_abbreviation": "WA", "full_county_name": "King County", "county_name": "King", "feat_class": "Populated Place", "primary_latitude": "47.75", "primary_longitude": "-122.28", "name": "Lake Forest Park"}, {"link_title": null, "guid": "a4811d91a5fa4e4d9281f0b35fa4efcd", "description": null, "fips_class": "H1", "url": "http://www.co.adams.wa.us/", "feature_id": "39538", "state_name": "Washington", "fips_county_cd": "1", "state_abbreviation": "WA", "full_county_name": null, "county_name": null, "feat_class": "Civil", "primary_latitude": "46.98", "primary_longitude": "-118.51", "name": "Adams County"}, {"link_title": null, "guid": "9cc972901bde42dd820c3a12158dd5a5", "description": null, "fips_class": "C1", "url": "http://www.ci.lake-stevens.wa.us/", "feature_id": "34163", "state_name": "Washington", "fips_county_cd": "61", "state_abbreviation": "WA", "full_county_name": "Snohomish County", "county_name": "Snohomish", "feat_class": "Populated Place", "primary_latitude": "48.01", "primary_longitude": "-122.06", "name": "Lake Stevens"}, {"link_title": null, "guid": "f5f69e3b9cd544e3a99ca3c9c57f0bae", "description": null, "fips_class": "H1", "url": "http://www.co.asotin.wa.us/", "feature_id": "39539", "state_name": "Washington", "fips_county_cd": "3", "state_abbreviation": "WA", "full_county_name": null, "county_name": null, "feat_class": "Civil", "primary_latitude": "46.19", "primary_longitude": "-117.18", "name": "Asotin County"}, {"link_title": null, "guid": "875d044d6221488d833d942317ac015d", "description": null, "fips_class": "C1", "url": "http://www.cityoflakewood.us/", "feature_id": "34164", "state_name": "Washington", "fips_county_cd": "53", "state_abbreviation": "WA", "full_county_name": "Pierce County", "county_name": "Pierce", "feat_class": "Populated Place", "primary_latitude": "47.17", "primary_longitude": "-122.51", "name": "Lakewood"}, {"link_title": null, "guid": "937d3814582b463db3b679fd00f61d2e", "description": null, "fips_class": "H1", "url": "http://www.co.benton.wa.us/", "feature_id": "39540", "state_name": "Washington", "fips_county_cd": "5", "state_abbreviation": "WA", "full_county_name": null, "county_name": null, "feat_class": "Civil", "primary_latitude": "46.26", "primary_longitude": "-119.48", "name": "Benton County"}, {"link_title": null, "guid": "e609da1db961460485254aa6dfa8fb24", "description": null, "fips_class": "H1", "url": "http://www.co.chelan.wa.us/", "feature_id": "39541", "state_name": "Washington", "fips_county_cd": "7", "state_abbreviation": "WA", "full_county_name": null, "county_name": null, "feat_class": "Civil", "primary_latitude": "47.88", "primary_longitude": "-120.63", "name": "Chelan County"}, {"link_title": null, "guid": "3a9437b3df9541ad9ee33b9ccdf07919", "description": null, "fips_class": "H1", "url": "http://www.clallam.net/", "feature_id": "39542", "state_name": "Washington", "fips_county_cd": "9", "state_abbreviation": "WA", "full_county_name": null, "county_name": null, "feat_class": "Civil", "primary_latitude": "48.04", "primary_longitude": "-123.83", "name": "Clallam County"}, {"link_title": null, "guid": "54242aec3d37444abfc2f3181c410e0d", "description": null, "fips_class": "H1", "url": "http://www.co.clark.wa.us/", "feature_id": "39543", "state_name": "Washington", "fips_county_cd": "11", "state_abbreviation": "WA", "full_county_name": null, "county_name": null, "feat_class": "Civil", "primary_latitude": "45.79", "primary_longitude": "-122.48", "name": "Clark County"}, {"link_title": null, "guid": "e58c1def7f9d492bbf5fe82ccd54e25c", "description": null, "fips_class": "H1", "url": "http://www.columbiaco.com/", "feature_id": "39544", "state_name": "Washington", "fips_county_cd": "13", "state_abbreviation": "WA", "full_county_name": null, "county_name": null, "feat_class": "Civil", "primary_latitude": "46.29", "primary_longitude": "-117.93", "name": "Columbia County"}, {"link_title": null, "guid": "be17d4ffddd0440bb953eaef842f5338", "description": null, "fips_class": "H1", "url": "http://www.co.cowlitz.wa.us/", "feature_id": "39545", "state_name": "Washington", "fips_county_cd": "15", "state_abbreviation": "WA", "full_county_name": null, "county_name": null, "feat_class": "Civil", "primary_latitude": "46.19", "primary_longitude": "-122.68", "name": "Cowlitz County"}, {"link_title": null, "guid": "dc214a17fa6e41c3b22e4a019b88383d", "description": null, "fips_class": "H1", "url": "http://www.douglascountywa.net/", "feature_id": "39546", "state_name": "Washington", "fips_county_cd": "17", "state_abbreviation": "WA", "full_county_name": null, "county_name": null, "feat_class": "Civil", "primary_latitude": "47.71", "primary_longitude": "-119.73", "name": "Douglas County"}, {"link_title": null, "guid": "9511203bb70f4e1294a3ea501f10e2b1", "description": null, "fips_class": "C1", "url": "http://www.mylongview.com/", "feature_id": "34172", "state_name": "Washington", "fips_county_cd": "15", "state_abbreviation": "WA", "full_county_name": "Cowlitz County", "county_name": "Cowlitz", "feat_class": "Populated Place", "primary_latitude": "46.13", "primary_longitude": "-122.93", "name": "Longview"}, {"link_title": null, "guid": "6c5b2754d0f2415bb1396314ccdd5e96", "description": null, "fips_class": "H1", "url": "http://www.co.franklin.wa.us/", "feature_id": "39548", "state_name": "Washington", "fips_county_cd": "21", "state_abbreviation": "WA", "full_county_name": null, "county_name": null, "feat_class": "Civil", "primary_latitude": "46.51", "primary_longitude": "-118.93", "name": "Franklin County"}, {"link_title": null, "guid": "0704631ec27442bdb595619a26153bdc", "description": null, "fips_class": "C1", "url": "http://www.lyndenwa.org/", "feature_id": "34174", "state_name": "Washington", "fips_county_cd": "73", "state_abbreviation": "WA", "full_county_name": "Whatcom County", "county_name": "Whatcom", "feat_class": "Populated Place", "primary_latitude": "48.94", "primary_longitude": "-122.45", "name": "Lynden"}, {"link_title": null, "guid": "fe31ef0dbc574a028a83d4cafb37f1dd", "description": null, "fips_class": "H1", "url": "http://www.co.grant.wa.us/", "feature_id": "39550", "state_name": "Washington", "fips_county_cd": "25", "state_abbreviation": "WA", "full_county_name": null, "county_name": null, "feat_class": "Civil", "primary_latitude": "47.14", "primary_longitude": "-119.48", "name": "Grant County"}, {"link_title": null, "guid": "c6a3c81c7de64848a9cf378fbadb7aab", "description": null, "fips_class": "C1", "url": "http://www.ci.lynnwood.wa.us/", "feature_id": "34175", "state_name": "Washington", "fips_county_cd": "61", "state_abbreviation": "WA", "full_county_name": "Snohomish County", "county_name": "Snohomish", "feat_class": "Populated Place", "primary_latitude": "47.82", "primary_longitude": "-122.31", "name": "Lynnwood"}, {"link_title": null, "guid": "a66137b7db564262b06c3f754429f34b", "description": null, "fips_class": "H1", "url": "http://www.co.grays-harbor.wa.us/", "feature_id": "39551", "state_name": "Washington", "fips_county_cd": "27", "state_abbreviation": "WA", "full_county_name": null, "county_name": null, "feat_class": "Civil", "primary_latitude": "47.08", "primary_longitude": "-123.83", "name": "Grays Harbor County"}, {"link_title": null, "guid": "a5d1cc057a0d4b4f93668ce177887552", "description": null, "fips_class": "H1", "url": "http://www.islandcounty.net/", "feature_id": "39552", "state_name": "Washington", "fips_county_cd": "29", "state_abbreviation": "WA", "full_county_name": null, "county_name": null, "feat_class": "Civil", "primary_latitude": "48.13", "primary_longitude": "-122.58", "name": "Island County"}, {"link_title": null, "guid": "7be8a644aa2d47a386c6095f70822d9e", "description": null, "fips_class": "H1", "url": "http://www.co.jefferson.wa.us/", "feature_id": "39553", "state_name": "Washington", "fips_county_cd": "31", "state_abbreviation": "WA", "full_county_name": null, "county_name": null, "feat_class": "Civil", "primary_latitude": "47.61", "primary_longitude": "-123.08", "name": "Jefferson County"}, {"link_title": null, "guid": "ab433a4aae73417c964c34e98b7c43d4", "description": null, "fips_class": "H1", "url": "http://www.kingcounty.gov/", "feature_id": "39554", "state_name": "Washington", "fips_county_cd": "33", "state_abbreviation": "WA", "full_county_name": null, "county_name": null, "feat_class": "Civil", "primary_latitude": "47.46", "primary_longitude": "-121.81", "name": "King County"}, {"link_title": null, "guid": "fbb2cbf3c7924bb988336a5259faff2f", "description": null, "fips_class": "C1", "url": "http://www.ci.maple-valley.wa.us/", "feature_id": "34179", "state_name": "Washington", "fips_county_cd": "33", "state_abbreviation": "WA", "full_county_name": "King County", "county_name": "King", "feat_class": "Populated Place", "primary_latitude": "47.4", "primary_longitude": "-122.03", "name": "Maple Valley"}, {"link_title": null, "guid": "3de6d50c920e4f38a0eee34f53439238", "description": null, "fips_class": "H1", "url": "http://www.kitsapgov.com/", "feature_id": "39555", "state_name": "Washington", "fips_county_cd": "35", "state_abbreviation": "WA", "full_county_name": null, "county_name": null, "feat_class": "Civil", "primary_latitude": "47.61", "primary_longitude": "-122.66", "name": "Kitsap County"}, {"link_title": null, "guid": "30a2cdb8a87546c480d231e1187d886c", "description": null, "fips_class": "H1", "url": "http://www.co.kittitas.wa.us/", "feature_id": "39556", "state_name": "Washington", "fips_county_cd": "37", "state_abbreviation": "WA", "full_county_name": null, "county_name": null, "feat_class": "Civil", "primary_latitude": "47.11", "primary_longitude": "-120.68", "name": "Kittitas County"}, {"link_title": null, "guid": "3b20039eaab1420ea8a80a54d19d6cf5", "description": null, "fips_class": "H1", "url": "http://www.klickitatcounty.org/", "feature_id": "39557", "state_name": "Washington", "fips_county_cd": "39", "state_abbreviation": "WA", "full_county_name": null, "county_name": null, "feat_class": "Civil", "primary_latitude": "45.86", "primary_longitude": "-120.76", "name": "Klickitat County"}, {"link_title": null, "guid": "12e39ce33f84453a8baacf5556b0ab50", "description": null, "fips_class": "C1", "url": "http://ci.marysville.wa.us/", "feature_id": "34182", "state_name": "Washington", "fips_county_cd": "61", "state_abbreviation": "WA", "full_county_name": "Snohomish County", "county_name": "Snohomish", "feat_class": "Populated Place", "primary_latitude": "48.05", "primary_longitude": "-122.17", "name": "Marysville"}, {"link_title": null, "guid": "b2f9684eef6648969e1426ccc6e60240", "description": null, "fips_class": "H1", "url": "http://lewiscountywa.gov/", "feature_id": "39558", "state_name": "Washington", "fips_county_cd": "41", "state_abbreviation": "WA", "full_county_name": null, "county_name": null, "feat_class": "Civil", "primary_latitude": "46.58", "primary_longitude": "-122.4", "name": "Lewis County"}, {"link_title": null, "guid": "53613ba137f242279f5b91b35265e300", "description": null, "fips_class": "H1", "url": "http://www.co.mason.wa.us/", "feature_id": "39560", "state_name": "Washington", "fips_county_cd": "45", "state_abbreviation": "WA", "full_county_name": null, "county_name": null, "feat_class": "Civil", "primary_latitude": "47.34", "primary_longitude": "-123.18", "name": "Mason County"}, {"link_title": null, "guid": "e991111642d140d38f5aa6bc3919d2dd", "description": null, "fips_class": "C1", "url": "http://www.medical-lake.org/", "feature_id": "34185", "state_name": "Washington", "fips_county_cd": "63", "state_abbreviation": "WA", "full_county_name": "Spokane County", "county_name": "Spokane", "feat_class": "Populated Place", "primary_latitude": "47.57", "primary_longitude": "-117.68", "name": "Medical Lake"}, {"link_title": null, "guid": "b516cff7b8a945b18d65755f57cab42b", "description": null, "fips_class": "H1", "url": "http://www.okanogancounty.org/", "feature_id": "39561", "state_name": "Washington", "fips_county_cd": "47", "state_abbreviation": "WA", "full_county_name": null, "county_name": null, "feat_class": "Civil", "primary_latitude": "48.54", "primary_longitude": "-119.73", "name": "Okanogan County"}, {"link_title": null, "guid": "00de5afb8ab744f1853a61c6570c077b", "description": null, "fips_class": "C1", "url": "http://www.medina-wa.gov/", "feature_id": "34186", "state_name": "Washington", "fips_county_cd": "33", "state_abbreviation": "WA", "full_county_name": "King County", "county_name": "King", "feat_class": "Populated Place", "primary_latitude": "47.62", "primary_longitude": "-122.22", "name": "Medina"}, {"link_title": null, "guid": "a8ce4f154d14487cbf963a774bd454a0", "description": null, "fips_class": "H1", "url": "http://www.co.pacific.wa.us/", "feature_id": "39562", "state_name": "Washington", "fips_county_cd": "49", "state_abbreviation": "WA", "full_county_name": null, "county_name": null, "feat_class": "Civil", "primary_latitude": "46.56", "primary_longitude": "-123.71", "name": "Pacific County"}, {"link_title": null, "guid": "49cb3e2ddeb64dbba536ba974a0f3320", "description": null, "fips_class": "C1", "url": "http://www.mercergov.org/", "feature_id": "34187", "state_name": "Washington", "fips_county_cd": "33", "state_abbreviation": "WA", "full_county_name": "King County", "county_name": "King", "feat_class": "Populated Place", "primary_latitude": "47.57", "primary_longitude": "-122.22", "name": "Mercer Island"}, {"link_title": null, "guid": "6a0b4c3c44e947b199a6718f9c3a79ec", "description": null, "fips_class": "H1", "url": "http://www.pendoreilleco.org/", "feature_id": "39563", "state_name": "Washington", "fips_county_cd": "51", "state_abbreviation": "WA", "full_county_name": null, "county_name": null, "feat_class": "Civil", "primary_latitude": "48.53", "primary_longitude": "-117.28", "name": "Pend Oreille County"}, {"link_title": null, "guid": "72cb7519853842918be47b620bb158fd", "description": null, "fips_class": "H1", "url": "http://www.co.pierce.wa.us/", "feature_id": "39564", "state_name": "Washington", "fips_county_cd": "53", "state_abbreviation": "WA", "full_county_name": null, "county_name": null, "feat_class": "Civil", "primary_latitude": "47.03", "primary_longitude": "-122.11", "name": "Pierce County"}, {"link_title": null, "guid": "4f7451516311402297d098a071f90417", "description": null, "fips_class": "H1", "url": "http://www.co.san-juan.wa.us/", "feature_id": "39565", "state_name": "Washington", "fips_county_cd": "55", "state_abbreviation": "WA", "full_county_name": null, "county_name": null, "feat_class": "Civil", "primary_latitude": "48.56", "primary_longitude": "-122.96", "name": "San Juan County"}, {"link_title": null, "guid": "075b78acb0224d1cb3abc49fbfd50d74", "description": null, "fips_class": "H1", "url": "http://www.skagitcounty.net/", "feature_id": "39566", "state_name": "Washington", "fips_county_cd": "57", "state_abbreviation": "WA", "full_county_name": null, "county_name": null, "feat_class": "Civil", "primary_latitude": "48.46", "primary_longitude": "-121.78", "name": "Skagit County"}, {"link_title": null, "guid": "5a51490461dc4073b78f817f248653a5", "description": null, "fips_class": "C1", "url": "http://www.cityofmillcreek.com/", "feature_id": "34191", "state_name": "Washington", "fips_county_cd": "61", "state_abbreviation": "WA", "full_county_name": "Snohomish County", "county_name": "Snohomish", "feat_class": "Populated Place", "primary_latitude": "47.86", "primary_longitude": "-122.2", "name": "Mill Creek"}, {"link_title": null, "guid": "40df870040dd45b48b893c19e11bcfb3", "description": null, "fips_class": "H1", "url": "http://www.skamaniacounty.org/", "feature_id": "39567", "state_name": "Washington", "fips_county_cd": "59", "state_abbreviation": "WA", "full_county_name": null, "county_name": null, "feat_class": "Civil", "primary_latitude": "46.03", "primary_longitude": "-121.9", "name": "Skamania County"}, {"link_title": null, "guid": "7019dad503f44aed8253e9a6f6ab9baf", "description": null, "fips_class": "H1", "url": "http://www.co.snohomish.wa.us/", "feature_id": "39568", "state_name": "Washington", "fips_county_cd": "61", "state_abbreviation": "WA", "full_county_name": null, "county_name": null, "feat_class": "Civil", "primary_latitude": "48.04", "primary_longitude": "-121.71", "name": "Snohomish County"}, {"link_title": null, "guid": "18aab3146fa14fcba828153dae8680a0", "description": null, "fips_class": "C1", "url": "http://www.cityofmilton.net/", "feature_id": "34193", "state_name": "Washington", "fips_county_cd": "53", "state_abbreviation": "WA", "full_county_name": "Pierce County", "county_name": "Pierce", "feat_class": "Populated Place", "primary_latitude": "47.24", "primary_longitude": "-122.31", "name": "Milton"}, {"link_title": null, "guid": "74d2cb65729a4fa4baeba2a0afddd085", "description": null, "fips_class": "H1", "url": "http://www.spokanecounty.org/", "feature_id": "39569", "state_name": "Washington", "fips_county_cd": "63", "state_abbreviation": "WA", "full_county_name": null, "county_name": null, "feat_class": "Civil", "primary_latitude": "47.61", "primary_longitude": "-117.36", "name": "Spokane County"}, {"link_title": null, "guid": "6f99d28ca8c345dc8931af439595bcc1", "description": null, "fips_class": "C1", "url": "http://www.ci.monroe.wa.us/", "feature_id": "34194", "state_name": "Washington", "fips_county_cd": "61", "state_abbreviation": "WA", "full_county_name": "Snohomish County", "county_name": "Snohomish", "feat_class": "Populated Place", "primary_latitude": "47.85", "primary_longitude": "-121.97", "name": "Monroe"}, {"link_title": null, "guid": "d91286eb028941fd8e8d05545bbe5337", "description": null, "fips_class": "H1", "url": "http://www.co.stevens.wa.us/", "feature_id": "39570", "state_name": "Washington", "fips_county_cd": "65", "state_abbreviation": "WA", "full_county_name": null, "county_name": null, "feat_class": "Civil", "primary_latitude": "48.43", "primary_longitude": "-117.83", "name": "Stevens County"}, {"link_title": null, "guid": "e6d7e9d42a0344dea1c352c1c0b42e1e", "description": null, "fips_class": "C1", "url": "http://www.montesano.us/", "feature_id": "34195", "state_name": "Washington", "fips_county_cd": "27", "state_abbreviation": "WA", "full_county_name": "Grays Harbor County", "county_name": "Grays Harbor", "feat_class": "Populated Place", "primary_latitude": "46.98", "primary_longitude": "-123.6", "name": "Montesano"}, {"link_title": null, "guid": "5b3a2a5403ba4107894558481dcb0c18", "description": null, "fips_class": "H1", "url": "http://www.co.thurston.wa.us/", "feature_id": "39571", "state_name": "Washington", "fips_county_cd": "67", "state_abbreviation": "WA", "full_county_name": null, "county_name": null, "feat_class": "Civil", "primary_latitude": "46.91", "primary_longitude": "-122.81", "name": "Thurston County"}, {"link_title": null, "guid": "99a80da476594467b157ea4f32975426", "description": null, "fips_class": "H1", "url": "http://www.co.wahkiakum.wa.us/", "feature_id": "39572", "state_name": "Washington", "fips_county_cd": "69", "state_abbreviation": "WA", "full_county_name": null, "county_name": null, "feat_class": "Civil", "primary_latitude": "46.28", "primary_longitude": "-123.43", "name": "Wahkiakum County"}, {"link_title": null, "guid": "a1cc3c2f8e384747b6b0c542ae6b8430", "description": null, "fips_class": "H1", "url": "http://www.co.walla-walla.wa.us/", "feature_id": "39573", "state_name": "Washington", "fips_county_cd": "71", "state_abbreviation": "WA", "full_county_name": null, "county_name": null, "feat_class": "Civil", "primary_latitude": "46.28", "primary_longitude": "-118.48", "name": "Walla Walla County"}, {"link_title": null, "guid": "4b283ca15b8f462493125caea92fd2b7", "description": null, "fips_class": "H1", "url": "http://www.co.whatcom.wa.us/", "feature_id": "39574", "state_name": "Washington", "fips_county_cd": "73", "state_abbreviation": "WA", "full_county_name": null, "county_name": null, "feat_class": "Civil", "primary_latitude": "48.91", "primary_longitude": "-121.78", "name": "Whatcom County"}, {"link_title": null, "guid": "9aa0d1842dcc47e490f2ec20a415c638", "description": null, "fips_class": "C1", "url": "http://www.ci.mount-vernon.wa.us/", "feature_id": "34199", "state_name": "Washington", "fips_county_cd": "57", "state_abbreviation": "WA", "full_county_name": "Skagit County", "county_name": "Skagit", "feat_class": "Populated Place", "primary_latitude": "48.42", "primary_longitude": "-122.33", "name": "Mount Vernon"}, {"link_title": null, "guid": "5c1d622793114261b0440dab90b632ac", "description": null, "fips_class": "H1", "url": "http://www.whitmancounty.org/", "feature_id": "39575", "state_name": "Washington", "fips_county_cd": "75", "state_abbreviation": "WA", "full_county_name": null, "county_name": null, "feat_class": "Civil", "primary_latitude": "46.91", "primary_longitude": "-117.48", "name": "Whitman County"}, {"link_title": null, "guid": "8f7ee81d0f1344709a208844531406ed", "description": null, "fips_class": "C1", "url": "http://www.ci.mountlake-terrace.wa.us/", "feature_id": "34200", "state_name": "Washington", "fips_county_cd": "61", "state_abbreviation": "WA", "full_county_name": "Snohomish County", "county_name": "Snohomish", "feat_class": "Populated Place", "primary_latitude": "47.78", "primary_longitude": "-122.3", "name": "Mountlake Terrace"}, {"link_title": null, "guid": "970fbcb2bfee48519305fc5d2b8937ae", "description": null, "fips_class": "H1", "url": "http://www.yakimacounty.us", "feature_id": "39576", "state_name": "Washington", "fips_county_cd": "77", "state_abbreviation": "WA", "full_county_name": null, "county_name": null, "feat_class": "Civil", "primary_latitude": "46.46", "primary_longitude": "-120.66", "name": "Yakima County"}, {"link_title": null, "guid": "2b673ef1ad86441a84aabf5cd44ca0fe", "description": null, "fips_class": "C1", "url": "http://www.ci.mukilteo.wa.us/", "feature_id": "34202", "state_name": "Washington", "fips_county_cd": "61", "state_abbreviation": "WA", "full_county_name": "Snohomish County", "county_name": "Snohomish", "feat_class": "Populated Place", "primary_latitude": "47.94", "primary_longitude": "-122.3", "name": "Mukilteo"}, {"link_title": null, "guid": "2a9c965d48684aceab4d5e7697754f33", "description": null, "fips_class": "C1", "url": "http://www.ci.newcastle.wa.us/", "feature_id": "34206", "state_name": "Washington", "fips_county_cd": "33", "state_abbreviation": "WA", "full_county_name": "King County", "county_name": "King", "feat_class": "Populated Place", "primary_latitude": "47.53", "primary_longitude": "-122.15", "name": "Newcastle"}, {"link_title": null, "guid": "c07e847dfd7e4b5dbdb30bdc6f901255", "description": null, "fips_class": "C1", "url": "http://www.newport-wa.org/", "feature_id": "34207", "state_name": "Washington", "fips_county_cd": "51", "state_abbreviation": "WA", "full_county_name": "Pend Oreille County", "county_name": "Pend Oreille", "feat_class": "Populated Place", "primary_latitude": "48.17", "primary_longitude": "-117.04", "name": "Newport"}, {"link_title": null, "guid": "c0983f0a8449427c97e0607942de34bf", "description": null, "fips_class": "C1", "url": "http://www.ci.normandy-park.wa.us/", "feature_id": "34209", "state_name": "Washington", "fips_county_cd": "33", "state_abbreviation": "WA", "full_county_name": "King County", "county_name": "King", "feat_class": "Populated Place", "primary_latitude": "47.43", "primary_longitude": "-122.34", "name": "Normandy Park"}, {"link_title": null, "guid": "b78b35f0e1d5441680c7e452834207c4", "description": null, "fips_class": "C1", "url": "http://ci.north-bend.wa.us/", "feature_id": "34210", "state_name": "Washington", "fips_county_cd": "33", "state_abbreviation": "WA", "full_county_name": "King County", "county_name": "King", "feat_class": "Populated Place", "primary_latitude": "47.49", "primary_longitude": "-121.78", "name": "North Bend"}, {"link_title": null, "guid": "5c44b470224b4810a5bbdbf0436a97d7", "description": null, "fips_class": "C1", "url": "http://www.oakharbor.org/", "feature_id": "34213", "state_name": "Washington", "fips_county_cd": "29", "state_abbreviation": "WA", "full_county_name": "Island County", "county_name": "Island", "feat_class": "Populated Place", "primary_latitude": "48.29", "primary_longitude": "-122.64", "name": "Oak Harbor"}, {"link_title": null, "guid": "c08c38caa3324e18867bb1e40e8e852e", "description": null, "fips_class": "C1", "url": "http://www.osgov.com/", "feature_id": "34216", "state_name": "Washington", "fips_county_cd": "27", "state_abbreviation": "WA", "full_county_name": "Grays Harbor County", "county_name": "Grays Harbor", "feat_class": "Populated Place", "primary_latitude": "46.97", "primary_longitude": "-124.15", "name": "Ocean Shores"}, {"link_title": null, "guid": "ac689ac1dfea4d249b624e1a02763234", "description": null, "fips_class": "C1", "url": "http://olympiawa.gov/", "feature_id": "34219", "state_name": "Washington", "fips_county_cd": "67", "state_abbreviation": "WA", "full_county_name": "Thurston County", "county_name": "Thurston", "feat_class": "Populated Place", "primary_latitude": "47.03", "primary_longitude": "-122.9", "name": "Olympia"}, {"link_title": null, "guid": "44e988c2e4604429a4c7341132404d5b", "description": null, "fips_class": "C1", "url": "http://ci.pacific.wa.us/", "feature_id": "34224", "state_name": "Washington", "fips_county_cd": "33", "state_abbreviation": "WA", "full_county_name": "King County", "county_name": "King", "feat_class": "Populated Place", "primary_latitude": "47.26", "primary_longitude": "-122.25", "name": "Pacific"}, {"link_title": null, "guid": "abf7ebd0f0184be39e74152705fb7b47", "description": null, "fips_class": "C1", "url": "http://www.ci.pasco.wa.us/", "feature_id": "34226", "state_name": "Washington", "fips_county_cd": "21", "state_abbreviation": "WA", "full_county_name": "Franklin County", "county_name": "Franklin", "feat_class": "Populated Place", "primary_latitude": "46.23", "primary_longitude": "-119.1", "name": "Pasco"}, {"link_title": null, "guid": "2509088baa00472b93e45738533d6e54", "description": null, "fips_class": "C1", "url": "http://ci.port-angeles.wa.us/", "feature_id": "34230", "state_name": "Washington", "fips_county_cd": "9", "state_abbreviation": "WA", "full_county_name": "Clallam County", "county_name": "Clallam", "feat_class": "Populated Place", "primary_latitude": "48.11", "primary_longitude": "-123.43", "name": "Port Angeles"}, {"link_title": null, "guid": "894edbcdd4614c099367707a364863b7", "description": null, "fips_class": "C1", "url": "http://www.cityofpt.us/", "feature_id": "34232", "state_name": "Washington", "fips_county_cd": "31", "state_abbreviation": "WA", "full_county_name": "Jefferson County", "county_name": "Jefferson", "feat_class": "Populated Place", "primary_latitude": "48.11", "primary_longitude": "-122.76", "name": "Port Townsend"}, {"link_title": null, "guid": "a8db7d3d13b541ebb73f35d766054a49", "description": null, "fips_class": "C1", "url": "http://www.cityofpoulsbo.com/", "feature_id": "34233", "state_name": "Washington", "fips_county_cd": "35", "state_abbreviation": "WA", "full_county_name": "Kitsap County", "county_name": "Kitsap", "feat_class": "Populated Place", "primary_latitude": "47.73", "primary_longitude": "-122.64", "name": "Poulsbo"}, {"link_title": null, "guid": "8bb938dc4136494396512cf323d81451", "description": null, "fips_class": "C1", "url": "http://www.ci.pullman.wa.us/", "feature_id": "34236", "state_name": "Washington", "fips_county_cd": "75", "state_abbreviation": "WA", "full_county_name": "Whitman County", "county_name": "Whitman", "feat_class": "Populated Place", "primary_latitude": "46.73", "primary_longitude": "-117.17", "name": "Pullman"}, {"link_title": null, "guid": "a918e3dac0ad4224a21914c0e4b4c60e", "description": null, "fips_class": "C1", "url": "http://www.cityofpuyallup.org/", "feature_id": "34237", "state_name": "Washington", "fips_county_cd": "53", "state_abbreviation": "WA", "full_county_name": "Pierce County", "county_name": "Pierce", "feat_class": "Populated Place", "primary_latitude": "47.18", "primary_longitude": "-122.29", "name": "Puyallup"}, {"link_title": null, "guid": "746b17dc98d143fb9fc7812ce75e381b", "description": null, "fips_class": "C1", "url": "http://www.redmond.gov/", "feature_id": "34242", "state_name": "Washington", "fips_county_cd": "33", "state_abbreviation": "WA", "full_county_name": "King County", "county_name": "King", "feat_class": "Populated Place", "primary_latitude": "47.67", "primary_longitude": "-122.12", "name": "Redmond"}, {"link_title": null, "guid": "181ef5057f7540799ab4786a50440771", "description": null, "fips_class": "C1", "url": "http://www.rentonwa.gov/", "feature_id": "34243", "state_name": "Washington", "fips_county_cd": "33", "state_abbreviation": "WA", "full_county_name": "King County", "county_name": "King", "feat_class": "Populated Place", "primary_latitude": "47.48", "primary_longitude": "-122.21", "name": "Renton"}, {"link_title": null, "guid": "93607e25bcf94ea79ad751f7e27bbd4e", "description": null, "fips_class": "C1", "url": "http://www.ci.richland.wa.us/", "feature_id": "34245", "state_name": "Washington", "fips_county_cd": "5", "state_abbreviation": "WA", "full_county_name": "Benton County", "county_name": "Benton", "feat_class": "Populated Place", "primary_latitude": "46.28", "primary_longitude": "-119.28", "name": "Richland"}, {"link_title": null, "guid": "df6edf87377f446db1da4e73921c6fa9", "description": null, "fips_class": "C1", "url": "http://www.ci.sammamish.wa.us/", "feature_id": "34257", "state_name": "Washington", "fips_county_cd": "33", "state_abbreviation": "WA", "full_county_name": "King County", "county_name": "King", "feat_class": "Populated Place", "primary_latitude": "47.64", "primary_longitude": "-122.08", "name": "Sammamish"}, {"link_title": null, "guid": "9d3bb0fa50454b71bf208efa9a462d11", "description": null, "fips_class": "C1", "url": "http://seattle.gov/", "feature_id": "34259", "state_name": "Washington", "fips_county_cd": "33", "state_abbreviation": "WA", "full_county_name": "King County", "county_name": "King", "feat_class": "Populated Place", "primary_latitude": "47.6", "primary_longitude": "-122.33", "name": "Seattle"}, {"link_title": null, "guid": "2d781c0d2be4450a91b6be04b208c4e5", "description": null, "fips_class": "C1", "url": "http://www.ci.sedro-woolley.wa.us/", "feature_id": "34260", "state_name": "Washington", "fips_county_cd": "57", "state_abbreviation": "WA", "full_county_name": "Skagit County", "county_name": "Skagit", "feat_class": "Populated Place", "primary_latitude": "48.5", "primary_longitude": "-122.23", "name": "Sedro-Woolley"}, {"link_title": null, "guid": "fad1e01fee3244e5ae63784b39d1fe96", "description": null, "fips_class": "C1", "url": "http://www.ci.selah.wa.us/", "feature_id": "34261", "state_name": "Washington", "fips_county_cd": "77", "state_abbreviation": "WA", "full_county_name": "Yakima County", "county_name": "Yakima", "feat_class": "Populated Place", "primary_latitude": "46.65", "primary_longitude": "-120.53", "name": "Selah"}, {"link_title": null, "guid": "72860ac2a7414885ad16196c508cf3eb", "description": null, "fips_class": "C1", "url": "http://www.ci.sequim.wa.us/", "feature_id": "34262", "state_name": "Washington", "fips_county_cd": "9", "state_abbreviation": "WA", "full_county_name": "Clallam County", "county_name": "Clallam", "feat_class": "Populated Place", "primary_latitude": "48.07", "primary_longitude": "-123.1", "name": "Sequim"}, {"link_title": null, "guid": "c6cb366a04ae4022923eb0dbe41fc42a", "description": null, "fips_class": "C1", "url": "http://www.ci.shelton.wa.us/", "feature_id": "34263", "state_name": "Washington", "fips_county_cd": "45", "state_abbreviation": "WA", "full_county_name": "Mason County", "county_name": "Mason", "feat_class": "Populated Place", "primary_latitude": "47.21", "primary_longitude": "-123.1", "name": "Shelton"}, {"link_title": null, "guid": "c3bf2c08ecda49b2b63c8cf41af364fb", "description": null, "fips_class": "C1", "url": "http://www.cityofshoreline.com/", "feature_id": "34264", "state_name": "Washington", "fips_county_cd": "33", "state_abbreviation": "WA", "full_county_name": "King County", "county_name": "King", "feat_class": "Populated Place", "primary_latitude": "47.75", "primary_longitude": "-122.34", "name": "Shoreline"}, {"link_title": null, "guid": "d93cd579ee0a4e91b895ef8db34c16b4", "description": null, "fips_class": "C1", "url": "http://www.ci.snohomish.wa.us/", "feature_id": "34266", "state_name": "Washington", "fips_county_cd": "61", "state_abbreviation": "WA", "full_county_name": "Snohomish County", "county_name": "Snohomish", "feat_class": "Populated Place", "primary_latitude": "47.91", "primary_longitude": "-122.09", "name": "Snohomish"}, {"link_title": null, "guid": "c218d97ea64941d89ec4003184d3d236", "description": null, "fips_class": "C1", "url": "http://www.ci.snoqualmie.wa.us/", "feature_id": "34267", "state_name": "Washington", "fips_county_cd": "33", "state_abbreviation": "WA", "full_county_name": "King County", "county_name": "King", "feat_class": "Populated Place", "primary_latitude": "47.52", "primary_longitude": "-121.82", "name": "Snoqualmie"}, {"link_title": null, "guid": "d83b8ff1ebc944aaba9c10ca8faf6aa8", "description": null, "fips_class": "C1", "url": "http://www.spokanecity.org/", "feature_id": "34273", "state_name": "Washington", "fips_county_cd": "63", "state_abbreviation": "WA", "full_county_name": "Spokane County", "county_name": "Spokane", "feat_class": "Populated Place", "primary_latitude": "47.65", "primary_longitude": "-117.42", "name": "Spokane"}, {"link_title": null, "guid": "c061b7ee3f9c494289cd4ae0eacd6230", "description": null, "fips_class": "C1", "url": "http://www.spokanevalley.org/", "feature_id": "34274", "state_name": "Washington", "fips_county_cd": "63", "state_abbreviation": "WA", "full_county_name": "Spokane County", "county_name": "Spokane", "feat_class": "Populated Place", "primary_latitude": "47.67", "primary_longitude": "-117.23", "name": "Spokane Valley"}, {"link_title": null, "guid": "1d7b7acaef3e4e428dd0c043765a3457", "description": null, "fips_class": "C1", "url": "http://www.ci.steilacoom.wa.us/", "feature_id": "34279", "state_name": "Washington", "fips_county_cd": "53", "state_abbreviation": "WA", "full_county_name": "Pierce County", "county_name": "Pierce", "feat_class": "Populated Place", "primary_latitude": "47.16", "primary_longitude": "-122.6", "name": "Steilacoom"}, {"link_title": null, "guid": "9324943fef1e4dce82c75e204764cc09", "description": null, "fips_class": "C1", "url": "http://www.ci.sultan.wa.us/", "feature_id": "34281", "state_name": "Washington", "fips_county_cd": "61", "state_abbreviation": "WA", "full_county_name": "Snohomish County", "county_name": "Snohomish", "feat_class": "Populated Place", "primary_latitude": "47.86", "primary_longitude": "-121.81", "name": "Sultan"}, {"link_title": null, "guid": "915ba124102d4f828db423d6fdc334e9", "description": null, "fips_class": "C1", "url": "http://www.ci.sumner.wa.us/", "feature_id": "34283", "state_name": "Washington", "fips_county_cd": "53", "state_abbreviation": "WA", "full_county_name": "Pierce County", "county_name": "Pierce", "feat_class": "Populated Place", "primary_latitude": "47.2", "primary_longitude": "-122.24", "name": "Sumner"}, {"link_title": null, "guid": "1b470db477dd43fdb9f7d2336bec082a", "description": null, "fips_class": "C1", "url": "http://www.ci.sunnyside.wa.us/", "feature_id": "34284", "state_name": "Washington", "fips_county_cd": "77", "state_abbreviation": "WA", "full_county_name": "Yakima County", "county_name": "Yakima", "feat_class": "Populated Place", "primary_latitude": "46.32", "primary_longitude": "-120", "name": "Sunnyside"}, {"link_title": null, "guid": "91c6c0ded262465c9851030daa5c2e02", "description": null, "fips_class": "C1", "url": "http://www.cityoftacoma.org/", "feature_id": "34285", "state_name": "Washington", "fips_county_cd": "53", "state_abbreviation": "WA", "full_county_name": "Pierce County", "county_name": "Pierce", "feat_class": "Populated Place", "primary_latitude": "47.25", "primary_longitude": "-122.44", "name": "Tacoma"}, {"link_title": null, "guid": "37f844f6eda3451aa4647ffd91db2dc4", "description": null, "fips_class": "C1", "url": "http://www.tonasketcity.org/", "feature_id": "34290", "state_name": "Washington", "fips_county_cd": "47", "state_abbreviation": "WA", "full_county_name": "Okanogan County", "county_name": "Okanogan", "feat_class": "Populated Place", "primary_latitude": "48.7", "primary_longitude": "-119.43", "name": "Tonasket"}, {"link_title": null, "guid": "3724ee36f36e491d951aabe3b8aae1f6", "description": null, "fips_class": "C1", "url": "http://www.ci.tumwater.wa.us/", "feature_id": "34293", "state_name": "Washington", "fips_county_cd": "67", "state_abbreviation": "WA", "full_county_name": "Thurston County", "county_name": "Thurston", "feat_class": "Populated Place", "primary_latitude": "47", "primary_longitude": "-122.9", "name": "Tumwater"}, {"link_title": null, "guid": "12361a9cf698484fae30bb4c3fe14b4a", "description": null, "fips_class": "C1", "url": "http://www.ci.union-gap.wa.us/", "feature_id": "34295", "state_name": "Washington", "fips_county_cd": "77", "state_abbreviation": "WA", "full_county_name": "Yakima County", "county_name": "Yakima", "feat_class": "Populated Place", "primary_latitude": "46.55", "primary_longitude": "-120.47", "name": "Union Gap"}, {"link_title": null, "guid": "8779f34b1c4d4e8fbe141431dcc747e9", "description": null, "fips_class": "C1", "url": "http://www.ci.university-place.wa.us/", "feature_id": "34297", "state_name": "Washington", "fips_county_cd": "53", "state_abbreviation": "WA", "full_county_name": "Pierce County", "county_name": "Pierce", "feat_class": "Populated Place", "primary_latitude": "47.23", "primary_longitude": "-122.55", "name": "University Place"}, {"link_title": null, "guid": "38d06dc2fc0e42cc9f62728041f51603", "description": null, "fips_class": "C1", "url": "http://www.aberdeeninfo.com/", "feature_id": "34042", "state_name": "Washington", "fips_county_cd": "27", "state_abbreviation": "WA", "full_county_name": "Grays Harbor County", "county_name": "Grays Harbor", "feat_class": "Populated Place", "primary_latitude": "46.97", "primary_longitude": "-123.81", "name": "Aberdeen"}, {"link_title": null, "guid": "b3007324488b4669834b47f7c09535c9", "description": null, "fips_class": "C1", "url": "http://www.cityofvancouver.us/", "feature_id": "34299", "state_name": "Washington", "fips_county_cd": "11", "state_abbreviation": "WA", "full_county_name": "Clark County", "county_name": "Clark", "feat_class": "Populated Place", "primary_latitude": "45.63", "primary_longitude": "-122.66", "name": "Vancouver"}, {"link_title": null, "guid": "912c1cf44544437d824191212433a98d", "description": null, "fips_class": "C1", "url": "http://www.ci.walla-walla.wa.us/", "feature_id": "34301", "state_name": "Washington", "fips_county_cd": "71", "state_abbreviation": "WA", "full_county_name": "Walla Walla County", "county_name": "Walla Walla", "feat_class": "Populated Place", "primary_latitude": "46.06", "primary_longitude": "-118.34", "name": "Walla Walla"}, {"link_title": null, "guid": "4b6f2006eb7a41778f4476cd340e8d98", "description": null, "fips_class": "C1", "url": "http://www.town.almira.wa.us/", "feature_id": "34046", "state_name": "Washington", "fips_county_cd": "43", "state_abbreviation": "WA", "full_county_name": "Lincoln County", "county_name": "Lincoln", "feat_class": "Populated Place", "primary_latitude": "47.71", "primary_longitude": "-118.94", "name": "Almira"}, {"link_title": null, "guid": "1f40940db6384c52b9184772b8b37e71", "description": null, "fips_class": "C1", "url": "http://www.cityofanacortes.org/", "feature_id": "34047", "state_name": "Washington", "fips_county_cd": "57", "state_abbreviation": "WA", "full_county_name": "Skagit County", "county_name": "Skagit", "feat_class": "Populated Place", "primary_latitude": "48.51", "primary_longitude": "-122.61", "name": "Anacortes"}]